elections/__init__.py
elections/democracy_works.py
elections/google_civic.py
elections/ipu_parline.py
elections/nytimes.py
elections/openfec.py
elections-0.0.3.dist-info/licenses/LICENSE
elections-0.0.3.dist-info/METADATA
elections-0.0.3.dist-info/WHEEL
elections-0.0.3.dist-info/top_level.txt
elections-0.0.3.dist-info/RECORD
