Metadata-Version: 2.4
Name: elections
Version: 0.0.3
Summary: There's a bit of an air of mystery around this project...
Home-page: https://github.com/thorwhalen/elections
Author: Thor Whalen
License: mit
Platform: any
License-File: LICENSE
Provides-Extra: testing
Dynamic: description
Dynamic: description-content-type
Dynamic: license-file
